[
  {
    "timestamp": "2026-01-11T06:40:31.833Z",
    "subscriberCount": "2470",
    "viewCount": "649672",
    "thumbnailUrl": "https://yt3.ggpht.com/DsBciWMYUvDnhffQdzdDAD6mM5mBspE0y7bhCUw8hsKoXWW0ht3ZSC8-HS5z3jf60q68pdCHJw=s800-c-k-c0x00ffffff-no-rj",
    "channelTitle": "Quiche19"
  },
  {
    "timestamp": "2026-01-11T12:53:49.886Z",
    "subscriberCount": "2480",
    "viewCount": "663567",
    "thumbnailUrl": "https://yt3.ggpht.com/DsBciWMYUvDnhffQdzdDAD6mM5mBspE0y7bhCUw8hsKoXWW0ht3ZSC8-HS5z3jf60q68pdCHJw=s800-c-k-c0x00ffffff-no-rj",
    "channelTitle": "Quiche19"
  },
  {
    "timestamp": "2026-01-11T18:36:56.215Z",
    "subscriberCount": "2490",
    "viewCount": "666719",
    "thumbnailUrl": "https://yt3.ggpht.com/DsBciWMYUvDnhffQdzdDAD6mM5mBspE0y7bhCUw8hsKoXWW0ht3ZSC8-HS5z3jf60q68pdCHJw=s800-c-k-c0x00ffffff-no-rj",
    "channelTitle": "Quiche19"
  },
  {
    "timestamp": "2026-01-12T02:22:14.905Z",
    "subscriberCount": "2520",
    "viewCount": "666719",
    "thumbnailUrl": "https://yt3.ggpht.com/DsBciWMYUvDnhffQdzdDAD6mM5mBspE0y7bhCUw8hsKoXWW0ht3ZSC8-HS5z3jf60q68pdCHJw=s800-c-k-c0x00ffffff-no-rj",
    "channelTitle": "Quiche19"
  },
  {
    "timestamp": "2026-01-12T06:47:14.074Z",
    "subscriberCount": "2520",
    "viewCount": "674407",
    "thumbnailUrl": "https://yt3.ggpht.com/DsBciWMYUvDnhffQdzdDAD6mM5mBspE0y7bhCUw8hsKoXWW0ht3ZSC8-HS5z3jf60q68pdCHJw=s800-c-k-c0x00ffffff-no-rj",
    "channelTitle": "Quiche19"
  },
  {
    "timestamp": "2026-01-12T13:00:51.658Z",
    "subscriberCount": "2530",
    "viewCount": "674407",
    "thumbnailUrl": "https://yt3.ggpht.com/DsBciWMYUvDnhffQdzdDAD6mM5mBspE0y7bhCUw8hsKoXWW0ht3ZSC8-HS5z3jf60q68pdCHJw=s800-c-k-c0x00ffffff-no-rj",
    "channelTitle": "Quiche19"
  },
  {
    "timestamp": "2026-01-12T18:41:33.093Z",
    "subscriberCount": "2540",
    "viewCount": "679888",
    "thumbnailUrl": "https://yt3.ggpht.com/DsBciWMYUvDnhffQdzdDAD6mM5mBspE0y7bhCUw8hsKoXWW0ht3ZSC8-HS5z3jf60q68pdCHJw=s800-c-k-c0x00ffffff-no-rj",
    "channelTitle": "Quiche19"
  },
  {
    "timestamp": "2026-01-13T02:07:20.787Z",
    "subscriberCount": "2560",
    "viewCount": "679888",
    "thumbnailUrl": "https://yt3.ggpht.com/DsBciWMYUvDnhffQdzdDAD6mM5mBspE0y7bhCUw8hsKoXWW0ht3ZSC8-HS5z3jf60q68pdCHJw=s800-c-k-c0x00ffffff-no-rj",
    "channelTitle": "Quiche19"
  },
  {
    "timestamp": "2026-01-13T06:43:15.478Z",
    "subscriberCount": "2560",
    "viewCount": "685338",
    "thumbnailUrl": "https://yt3.ggpht.com/DsBciWMYUvDnhffQdzdDAD6mM5mBspE0y7bhCUw8hsKoXWW0ht3ZSC8-HS5z3jf60q68pdCHJw=s800-c-k-c0x00ffffff-no-rj",
    "channelTitle": "Quiche19"
  },
  {
    "timestamp": "2026-01-13T13:00:49.030Z",
    "subscriberCount": "2560",
    "viewCount": "685338",
    "thumbnailUrl": "https://yt3.ggpht.com/DsBciWMYUvDnhffQdzdDAD6mM5mBspE0y7bhCUw8hsKoXWW0ht3ZSC8-HS5z3jf60q68pdCHJw=s800-c-k-c0x00ffffff-no-rj",
    "channelTitle": "Quiche19"
  },
  {
    "timestamp": "2026-01-13T18:39:21.670Z",
    "subscriberCount": "2570",
    "viewCount": "689913",
    "thumbnailUrl": "https://yt3.ggpht.com/DsBciWMYUvDnhffQdzdDAD6mM5mBspE0y7bhCUw8hsKoXWW0ht3ZSC8-HS5z3jf60q68pdCHJw=s800-c-k-c0x00ffffff-no-rj",
    "channelTitle": "Quiche19"
  },
  {
    "timestamp": "2026-01-14T02:20:53.524Z",
    "subscriberCount": "2590",
    "viewCount": "689913",
    "thumbnailUrl": "https://yt3.ggpht.com/DsBciWMYUvDnhffQdzdDAD6mM5mBspE0y7bhCUw8hsKoXWW0ht3ZSC8-HS5z3jf60q68pdCHJw=s800-c-k-c0x00ffffff-no-rj",
    "channelTitle": "Quiche19"
  },
  {
    "timestamp": "2026-01-14T06:43:34.357Z",
    "subscriberCount": "2590",
    "viewCount": "689913",
    "thumbnailUrl": "https://yt3.ggpht.com/DsBciWMYUvDnhffQdzdDAD6mM5mBspE0y7bhCUw8hsKoXWW0ht3ZSC8-HS5z3jf60q68pdCHJw=s800-c-k-c0x00ffffff-no-rj",
    "channelTitle": "Quiche19"
  },
  {
    "timestamp": "2026-01-14T13:00:25.654Z",
    "subscriberCount": "2600",
    "viewCount": "694934",
    "thumbnailUrl": "https://yt3.ggpht.com/DsBciWMYUvDnhffQdzdDAD6mM5mBspE0y7bhCUw8hsKoXWW0ht3ZSC8-HS5z3jf60q68pdCHJw=s800-c-k-c0x00ffffff-no-rj",
    "channelTitle": "Quiche19"
  },
  {
    "timestamp": "2026-01-14T18:41:49.063Z",
    "subscriberCount": "2600",
    "viewCount": "699980",
    "thumbnailUrl": "https://yt3.ggpht.com/DsBciWMYUvDnhffQdzdDAD6mM5mBspE0y7bhCUw8hsKoXWW0ht3ZSC8-HS5z3jf60q68pdCHJw=s800-c-k-c0x00ffffff-no-rj",
    "channelTitle": "Quiche19"
  },
  {
    "timestamp": "2026-01-15T02:08:57.701Z",
    "subscriberCount": "2610",
    "viewCount": "699980",
    "thumbnailUrl": "https://yt3.ggpht.com/DsBciWMYUvDnhffQdzdDAD6mM5mBspE0y7bhCUw8hsKoXWW0ht3ZSC8-HS5z3jf60q68pdCHJw=s800-c-k-c0x00ffffff-no-rj",
    "channelTitle": "Quiche19"
  },
  {
    "timestamp": "2026-01-15T06:42:48.147Z",
    "subscriberCount": "2620",
    "viewCount": "702409",
    "thumbnailUrl": "https://yt3.ggpht.com/DsBciWMYUvDnhffQdzdDAD6mM5mBspE0y7bhCUw8hsKoXWW0ht3ZSC8-HS5z3jf60q68pdCHJw=s800-c-k-c0x00ffffff-no-rj",
    "channelTitle": "Quiche19"
  },
  {
    "timestamp": "2026-01-15T12:59:05.145Z",
    "subscriberCount": "2620",
    "viewCount": "702409",
    "thumbnailUrl": "https://yt3.ggpht.com/DsBciWMYUvDnhffQdzdDAD6mM5mBspE0y7bhCUw8hsKoXWW0ht3ZSC8-HS5z3jf60q68pdCHJw=s800-c-k-c0x00ffffff-no-rj",
    "channelTitle": "Quiche19"
  },
  {
    "timestamp": "2026-01-15T18:46:14.342Z",
    "subscriberCount": "2630",
    "viewCount": "707529",
    "thumbnailUrl": "https://yt3.ggpht.com/DsBciWMYUvDnhffQdzdDAD6mM5mBspE0y7bhCUw8hsKoXWW0ht3ZSC8-HS5z3jf60q68pdCHJw=s800-c-k-c0x00ffffff-no-rj",
    "channelTitle": "Quiche19"
  },
  {
    "timestamp": "2026-01-16T02:11:06.601Z",
    "subscriberCount": "2640",
    "viewCount": "707529",
    "thumbnailUrl": "https://yt3.ggpht.com/DsBciWMYUvDnhffQdzdDAD6mM5mBspE0y7bhCUw8hsKoXWW0ht3ZSC8-HS5z3jf60q68pdCHJw=s800-c-k-c0x00ffffff-no-rj",
    "channelTitle": "Quiche19"
  },
  {
    "timestamp": "2026-01-16T06:42:45.584Z",
    "subscriberCount": "2640",
    "viewCount": "712144",
    "thumbnailUrl": "https://yt3.ggpht.com/DsBciWMYUvDnhffQdzdDAD6mM5mBspE0y7bhCUw8hsKoXWW0ht3ZSC8-HS5z3jf60q68pdCHJw=s800-c-k-c0x00ffffff-no-rj",
    "channelTitle": "Quiche19"
  },
  {
    "timestamp": "2026-01-16T12:58:16.996Z",
    "subscriberCount": "2650",
    "viewCount": "712144",
    "thumbnailUrl": "https://yt3.ggpht.com/DsBciWMYUvDnhffQdzdDAD6mM5mBspE0y7bhCUw8hsKoXWW0ht3ZSC8-HS5z3jf60q68pdCHJw=s800-c-k-c0x00ffffff-no-rj",
    "channelTitle": "Quiche19"
  },
  {
    "timestamp": "2026-01-16T18:41:20.293Z",
    "subscriberCount": "2660",
    "viewCount": "712144",
    "thumbnailUrl": "https://yt3.ggpht.com/DsBciWMYUvDnhffQdzdDAD6mM5mBspE0y7bhCUw8hsKoXWW0ht3ZSC8-HS5z3jf60q68pdCHJw=s800-c-k-c0x00ffffff-no-rj",
    "channelTitle": "Quiche19"
  },
  {
    "timestamp": "2026-01-17T02:04:57.181Z",
    "subscriberCount": "2660",
    "viewCount": "717120",
    "thumbnailUrl": "https://yt3.ggpht.com/DsBciWMYUvDnhffQdzdDAD6mM5mBspE0y7bhCUw8hsKoXWW0ht3ZSC8-HS5z3jf60q68pdCHJw=s800-c-k-c0x00ffffff-no-rj",
    "channelTitle": "Quiche19"
  },
  {
    "timestamp": "2026-01-17T06:39:00.727Z",
    "subscriberCount": "2660",
    "viewCount": "720775",
    "thumbnailUrl": "https://yt3.ggpht.com/DsBciWMYUvDnhffQdzdDAD6mM5mBspE0y7bhCUw8hsKoXWW0ht3ZSC8-HS5z3jf60q68pdCHJw=s800-c-k-c0x00ffffff-no-rj",
    "channelTitle": "Quiche19"
  },
  {
    "timestamp": "2026-01-17T12:52:27.920Z",
    "subscriberCount": "2670",
    "viewCount": "720775",
    "thumbnailUrl": "https://yt3.ggpht.com/DsBciWMYUvDnhffQdzdDAD6mM5mBspE0y7bhCUw8hsKoXWW0ht3ZSC8-HS5z3jf60q68pdCHJw=s800-c-k-c0x00ffffff-no-rj",
    "channelTitle": "Quiche19"
  },
  {
    "timestamp": "2026-01-17T18:36:29.063Z",
    "subscriberCount": "2670",
    "viewCount": "723203",
    "thumbnailUrl": "https://yt3.ggpht.com/DsBciWMYUvDnhffQdzdDAD6mM5mBspE0y7bhCUw8hsKoXWW0ht3ZSC8-HS5z3jf60q68pdCHJw=s800-c-k-c0x00ffffff-no-rj",
    "channelTitle": "Quiche19"
  },
  {
    "timestamp": "2026-01-18T02:24:51.679Z",
    "subscriberCount": "2680",
    "viewCount": "723203",
    "thumbnailUrl": "https://yt3.ggpht.com/DsBciWMYUvDnhffQdzdDAD6mM5mBspE0y7bhCUw8hsKoXWW0ht3ZSC8-HS5z3jf60q68pdCHJw=s800-c-k-c0x00ffffff-no-rj",
    "channelTitle": "Quiche19"
  },
  {
    "timestamp": "2026-01-18T06:39:41.054Z",
    "subscriberCount": "2690",
    "viewCount": "726317",
    "thumbnailUrl": "https://yt3.ggpht.com/DsBciWMYUvDnhffQdzdDAD6mM5mBspE0y7bhCUw8hsKoXWW0ht3ZSC8-HS5z3jf60q68pdCHJw=s800-c-k-c0x00ffffff-no-rj",
    "channelTitle": "Quiche19"
  },
  {
    "timestamp": "2026-01-18T12:52:29.856Z",
    "subscriberCount": "2690",
    "viewCount": "726317",
    "thumbnailUrl": "https://yt3.ggpht.com/DsBciWMYUvDnhffQdzdDAD6mM5mBspE0y7bhCUw8hsKoXWW0ht3ZSC8-HS5z3jf60q68pdCHJw=s800-c-k-c0x00ffffff-no-rj",
    "channelTitle": "Quiche19"
  }
]